app.py
kson2toml/__init__.py
kson2toml/ast.py
kson2toml/kson2toml.py
kson2toml-1.0.6.dist-info/licenses/LICENCE
kson2toml-1.0.6.dist-info/METADATA
kson2toml-1.0.6.dist-info/WHEEL
kson2toml-1.0.6.dist-info/entry_points.txt
kson2toml-1.0.6.dist-info/top_level.txt
kson2toml-1.0.6.dist-info/RECORD
