Metadata-Version: 2.4
Name: kson2toml
Version: 1.0.6
Summary: KSON to TOML converter
Author: Matias Barrios
Author-email: matias@barrioslira.com
License-File: LICENCE
Requires-Dist: kson-lang
Requires-Dist: toml
Dynamic: author
Dynamic: author-email
Dynamic: description
Dynamic: description-content-type
Dynamic: license-file
Dynamic: requires-dist
Dynamic: summary
